Metadata-Version: 2.1
Name: odoo13-addon-account-invoice-refund-line-selection
Version: 13.0.1.1.0
Summary: This module allows the user to refund specific lines in a invoice
Home-page: https://github.com/OCA/account-invoicing
Author: Creu Blanca, Odoo Community Association (OCA)
Author-email: support@odoo-community.org
License: LGPL-3
Platform: UNKNOWN
Classifier: Programming Language :: Python
Classifier: Framework :: Odoo
Classifier: Framework :: Odoo :: 13.0
Classifier: License :: OSI Approved :: GNU Lesser General Public License v3 (LGPLv3)
Requires-Python: >=3.5
Requires-Dist: odoo (<13.1dev,>=13.0a)
